{
  "build": "pyhd3eb1b0_0",
  "build_number": 0,
  "channel": "https://repo.anaconda.com/pkgs/main/noarch",
  "constrains": [],
  "depends": [
    "python >=3.6"
  ],
  "extracted_package_dir": "C:\\anaconda\\pkgs\\pycodestyle-2.8.0-pyhd3eb1b0_0",
  "features": "",
  "files": [
    "Lib/site-packages/pycodestyle-2.8.0.dist-info/INSTALLER",
    "Lib/site-packages/pycodestyle-2.8.0.dist-info/LICENSE",
    "Lib/site-packages/pycodestyle-2.8.0.dist-info/METADATA",
    "Lib/site-packages/pycodestyle-2.8.0.dist-info/RECORD",
    "Lib/site-packages/pycodestyle-2.8.0.dist-info/REQUESTED",
    "Lib/site-packages/pycodestyle-2.8.0.dist-info/WHEEL",
    "Lib/site-packages/pycodestyle-2.8.0.dist-info/direct_url.json",
    "Lib/site-packages/pycodestyle-2.8.0.dist-info/entry_points.txt",
    "Lib/site-packages/pycodestyle-2.8.0.dist-info/namespace_packages.txt",
    "Lib/site-packages/pycodestyle-2.8.0.dist-info/top_level.txt",
    "Lib/site-packages/pycodestyle.py",
    "Lib/site-packages/__pycache__/pycodestyle.cpython-39.pyc",
    "Scripts/pycodestyle-script.py",
    "Scripts/pycodestyle.exe"
  ],
  "fn": "pycodestyle-2.8.0-pyhd3eb1b0_0.conda",
  "legacy_bz2_md5": "95dcbb941c59c3710ee2d5fc15b3957d",
  "legacy_bz2_size": 39956,
  "license": "MIT",
  "license_family": "MIT",
  "link": {
    "source": "C:\\anaconda\\pkgs\\pycodestyle-2.8.0-pyhd3eb1b0_0",
    "type": 1
  },
  "md5": "50421e4349c5a89a729c7ba2b3a1ce7f",
  "name": "pycodestyle",
  "noarch": "python",
  "package_tarball_full_path": "C:\\anaconda\\pkgs\\pycodestyle-2.8.0-pyhd3eb1b0_0.conda",
  "package_type": "noarch_python",
  "paths_data": {
    "paths": [
      {
        "_path": "Lib/site-packages/__pycache__/pycodestyle.cpython-39.pyc",
        "path_type": "pyc_file"
      },
      {
        "_path": "Scripts/pycodestyle-script.py",
        "path_type": "windows_python_entry_point_script"
      }
    ],
    "paths_version": 1
  },
  "requested_spec": "pycodestyle==2.8.0=pyhd3eb1b0_0",
  "sha256": "cdbfa8be84770fea7fa1be3e057a7420c18dcddd604b280bc72447e9a0fc674d",
  "size": 41656,
  "subdir": "noarch",
  "timestamp": 1636635434503,
  "track_features": "",
  "url": "https://repo.anaconda.com/pkgs/main/noarch/pycodestyle-2.8.0-pyhd3eb1b0_0.conda",
  "version": "2.8.0"
}